conf_loaders/__init__.py
conf_loaders/encryption/__init__.py
conf_loaders/encryption/encryptor.py
conf_loaders/encryption/utils.py
conf_loaders/encryption/algorithms/__init__.py
conf_loaders/encryption/algorithms/aes.py
conf_loaders/encryption/algorithms/base.py
conf_loaders/encryption/algorithms/rsa.py
conf_loaders/utils/__init__.py
conf_loaders/utils/settings_load.py
conf_loaders/utils/settings_update.py
conf_loaders/utils/docrender_utils/__init__.py
conf_loaders/utils/docrender_utils/_yaml.py
conf_loaders/utils/docrender_utils/aliases.py
conf_loaders/utils/docrender_utils/files.py
conf_loaders/utils/docrender_utils/lock.py
conf_loaders/utils/docrender_utils/system.py
conf_loaders-0.3.0.dist-info/METADATA
conf_loaders-0.3.0.dist-info/WHEEL
conf_loaders-0.3.0.dist-info/top_level.txt
conf_loaders-0.3.0.dist-info/RECORD
